dd/__init__.py
dd/dd.py
datadot-1.0.0.dist-info/METADATA
datadot-1.0.0.dist-info/WHEEL
datadot-1.0.0.dist-info/RECORD
