Metadata-Version: 2.4
Name: datadot
Version: 1.0.0
Summary: A functional data navigation tool for Python
Requires-Python: >=3.8
